LICENSE
README.md
pyproject.toml
setup.py
frida_fusion/__init__.py
frida_fusion/__main__.py
frida_fusion/__meta__.py
frida_fusion/args.py
frida_fusion/config.py
frida_fusion/exceptions.py
frida_fusion/fusion.py
frida_fusion/module.py
frida_fusion.egg-info/PKG-INFO
frida_fusion.egg-info/SOURCES.txt
frida_fusion.egg-info/dependency_links.txt
frida_fusion.egg-info/entry_points.txt
frida_fusion.egg-info/requires.txt
frida_fusion.egg-info/top_level.txt
frida_fusion/libs/__init__.py
frida_fusion/libs/color.py
frida_fusion/libs/database.py
frida_fusion/libs/helpers.js
frida_fusion/libs/logger.py
frida_fusion/libs/scriptlocation.py
frida_fusion/modules/__init__.py
frida_fusion/modules/android_setings/__init__.py
frida_fusion/modules/android_setings/settings.js
frida_fusion/modules/android_setings/settings.py
frida_fusion/modules/crypto/__init__.py
frida_fusion/modules/crypto/crypto.js
frida_fusion/modules/crypto/crypto.py
frida_fusion/modules/hermes_injector/__init__.py
frida_fusion/modules/hermes_injector/hermes_hook.js
frida_fusion/modules/hermes_injector/hermes_injector.js
frida_fusion/modules/hermes_injector/hermes_injector.py
frida_fusion/modules/log/__init__.py
frida_fusion/modules/log/log.js
frida_fusion/modules/log/log.py
frida_fusion/modules/okhttp_logging/okhttp-logging.js
frida_fusion/modules/okhttp_logging/okhttp-logging.py
frida_fusion/modules/reflection/reflection-stalker.js
frida_fusion/modules/reflection/reflection-stalker.py
frida_fusion/modules/shared_preferences/__init__.py
frida_fusion/modules/shared_preferences/shared_preferences.js
frida_fusion/modules/shared_preferences/shared_preferences.py
frida_fusion/modules/tls_unpinning/__init__.py
frida_fusion/modules/tls_unpinning/frida_multiple_unpinning.py