Metadata-Version: 2.4
Name: frida-fusion
Version: 0.1.26
Summary: Hook your mobile tests with Frida
Author-email: "Helvio Junior (M4v3r1ck)" <helvio_junior@hotmail.com>
Maintainer-email: "Helvio Junior (M4v3r1ck)" <helvio_junior@hotmail.com>
Project-URL: Documentation, https://github.com/helviojunior/frida-fusion
Project-URL: Source, https://github.com/helviojunior/frida-fusion
Project-URL: Tracker, https://github.com/helviojunior/frida-fusion
Project-URL: Author, https://github.com/helviojunior
Keywords: Frida Fusion,Frida,Frida Scripts,development,red team
Classifier: Development Status :: 4 - Beta
Classifier: Environment :: Console
Classifier: Intended Audience :: System Administrators
Classifier: Natural Language :: English
Classifier: Operating System :: OS Independent
Classifier: Programming Language :: Python
Classifier: Programming Language :: Python :: 3
Classifier: Programming Language :: Python :: 3.9
Classifier: Programming Language :: Python :: 3.10
Classifier: Programming Language :: Python :: 3.11
Classifier: Programming Language :: Python :: 3.12
Classifier: Programming Language :: Python :: 3 :: Only
Classifier: Programming Language :: Python :: Implementation :: PyPy
Classifier: Topic :: Security
Classifier: Topic :: Utilities
Requires-Python: <4,>=3.9
License-File: LICENSE
Requires-Dist: colorama
Requires-Dist: requests>=2.23.0
Requires-Dist: frida>=15.1.17
Requires-Dist: frida-tools>=10.8.0
Dynamic: license-file
